{"info":[{"userId":1,"movieId":296,"rating":5.0,"timestamp":1147880044,"title":"Pulp Fiction"},{"userId":1,"movieId":306,"rating":3.5,"timestamp":1147868817,"title":"Three Colors: Red (Trois couleurs: Rouge)"},{"userId":1,"movieId":307,"rating":5.0,"timestamp":1147868828,"title":"Three Colors: Blue (Trois couleurs: Bleu)"},{"userId":1,"movieId":665,"rating":5.0,"timestamp":1147878820,"title":"Underground"},{"userId":1,"movieId":899,"rating":3.5,"timestamp":1147868510,"title":"Singin' in the Rain"},{"userId":1,"movieId":1088,"rating":4.0,"timestamp":1147868495,"title":"Dirty Dancing"},{"userId":1,"movieId":1175,"rating":3.5,"timestamp":1147868826, "title":"Delicatessen"},{"userId":1,"movieId":1217,"rating":3.5,"timestamp":1147878326,"title":"Ran"},{"userId":1,"movieId":1237,"rating":5.0,"timestamp":1147868839,"title":"Seventh Seal, The (Sjunde inseglet, Det)"},{"userId":1,"movieId":1250,"rating":4.0,"timestamp":1147868414,"title":"Bridge on the River Kwai, The"}]}